Metadata-Version: 2.1
Name: flask-http-signature
Version: 0.0.1
Summary: A Flask extension for HTTP Message Signatures
Home-page: https://github.com/pyauth/flask-http-signature
Author: Andrey Kislyuk
Author-email: kislyuk@gmail.com
License: Apache Software License
Platform: MacOS X
Platform: Posix
Classifier: Intended Audience :: Developers
Classifier: License :: OSI Approved :: Apache Software License
Classifier: Operating System :: MacOS :: MacOS X
Classifier: Operating System :: POSIX
Classifier: Programming Language :: Python
Classifier: Programming Language :: Python :: 3.7
Classifier: Programming Language :: Python :: 3.8
Classifier: Programming Language :: Python :: 3.9
Classifier: Programming Language :: Python :: 3.10
Classifier: Topic :: Software Development :: Libraries :: Python Modules
Classifier: Framework :: Flask
Provides-Extra: tests
